momo/__init__.py
momo/momo.py
momo/momo_adam.py
momo/types.py
momo_opt-0.1.0.dist-info/LICENSE
momo_opt-0.1.0.dist-info/METADATA
momo_opt-0.1.0.dist-info/WHEEL
momo_opt-0.1.0.dist-info/top_level.txt
momo_opt-0.1.0.dist-info/RECORD
