Metadata-Version: 2.1
Name: momo-opt
Version: 0.1.0
Summary: MoMo: Momentum Models for Adaptive Learning Rates
Home-page: https://github.com/fabian-sp/MoMo
Author: Fabian Schaipp
Author-email: fabian.schaipp@gmail.com
Classifier: Programming Language :: Python :: 3
Classifier: License :: OSI Approved :: MIT License
Classifier: Operating System :: OS Independent
Requires-Python: >=3.8.0
License-File: LICENSE
Requires-Dist: torch
Requires-Dist: numpy
